unratedwriting.py
unratedwriting-1.1.0.dist-info/LICENSE
unratedwriting-1.1.0.dist-info/METADATA
unratedwriting-1.1.0.dist-info/WHEEL
unratedwriting-1.1.0.dist-info/RECORD
