Metadata-Version: 2.1
Name: unratedwriting
Version: 1.1.0
Summary: A Python package that adds a typewriter effect to text output. It allows you to display text in a way that mimics the classic typewriter-style printing, with characters appearing one by one at a defined speed. This package is suitable for enhancing the visual appeal of command-line applications, creating interactive fiction games, or simply adding a fun twist to your Python projects. Easy to use and highly customizable, it provides an engaging way to present text-based information.
Home-page: https://github.com/AnozieChibuike/typewriter
License: MIT
Author: Anozie Chibuike
Author-email: chibuikeanozie0@gmail.com
Requires-Python: >=2.5
Classifier: License :: OSI Approved :: MIT License
Classifier: Programming Language :: Python :: 2
Classifier: Programming Language :: Python :: 2.7
Classifier: Programming Language :: Python :: 3
Classifier: Programming Language :: Python :: 3.4
Classifier: Programming Language :: Python :: 3.5
Classifier: Programming Language :: Python :: 3.6
Classifier: Programming Language :: Python :: 3.7
Classifier: Programming Language :: Python :: 3.8
Classifier: Programming Language :: Python :: 3.9
Classifier: Programming Language :: Python :: 3.10
Classifier: Programming Language :: Python :: 3.11
